gdcbeutils/__init__.py
gdcbeutils/AWS/Client.py
gdcbeutils/AWS/Services/DynamoDb.py
gdcbeutils/AWS/Services/ParameterStore.py
gdcbeutils/AWS/Services/SimpleQueueService.py
gdcbeutils/Api/__init__.py
gdcbeutils/Api/mail/__init__.py
gdcbeutils/database/__init__.py
gdcbeutils/database/mongodb.py
gdcbeutils/database/mysqldb.py
gdcbeutils/database/testing/__init__.py
gdcbeutils/database/testing/context.py
gdcbeutils/database/testing/decorator.py
gdcbeutils/models/__init__.py
gdcbeutils/models/pagination/__init__.py
gdcbeutils/models/pagination/paginated.py
gdcbeutils/models/pagination/paginated_results.py
gdcbeutils/parsing/__init__.py
gdcbeutils/parsing/date.py
gdcbeutils/parsing/dict.py
gdcbeutils-1.1.1.dist-info/METADATA
gdcbeutils-1.1.1.dist-info/WHEEL
gdcbeutils-1.1.1.dist-info/top_level.txt
gdcbeutils-1.1.1.dist-info/RECORD
